xifdr/__init__.py
xifdr/_version.py
xifdr/boosting.py
xifdr/fdr.py
xifdr/utils/column_preparation.py
xifdr/utils/expression_utils.py
xifdr/utils/guess_columns.py
xifdr/utils/knee_finder.py
xifdr-3.0.0a15.dist-info/METADATA
xifdr-3.0.0a15.dist-info/WHEEL
xifdr-3.0.0a15.dist-info/top_level.txt
xifdr-3.0.0a15.dist-info/RECORD
