Metadata-Version: 2.4
Name: xifdr
Version: 3.0.0a15
Summary: xiFDR: A tool for FDR analysis in cross-linking mass spectrometry
Author-email: "Falk B. Schimweg" <git@falk.schimweg.de>
License: AGPL-3.0-or-later
Project-URL: Homepage, https://github.com/Rappsilber-Laboratory/xiFDR-py
Project-URL: Documentation, https://xifdr-py.readthedocs.io
Project-URL: Repository, https://github.com/Rappsilber-Laboratory/xiFDR-py
Project-URL: Issues, https://github.com/Rappsilber-Laboratory/xiFDR-py/issues
Requires-Python: >=3.9
Requires-Dist: numpy
Requires-Dist: pandas
Requires-Dist: polars
Requires-Dist: scipy
Requires-Dist: psutil
Requires-Dist: pyarrow
Requires-Dist: setuptools_scm
Requires-Dist: kneed
